mcp_server_milvus/__init__.py
mcp_server_milvus/blogpost.md
mcp_server_milvus/example.env
mcp_server_milvus/server.py
mseep_mcp_server_milvus-0.1.5.dist-info/METADATA
mseep_mcp_server_milvus-0.1.5.dist-info/WHEEL
mseep_mcp_server_milvus-0.1.5.dist-info/entry_points.txt
mseep_mcp_server_milvus-0.1.5.dist-info/licenses/LICENSE
mseep_mcp_server_milvus-0.1.5.dist-info/RECORD
