Metadata-Version: 2.4
Name: mseep-mcp-server-milvus
Version: 0.1.5
Summary: MCP server for Milvus
Author-email: mseep <support@skydeck.ai>
License-File: LICENSE
Requires-Python: >=3.10
Requires-Dist: click>=8.0.0
Requires-Dist: fastmcp>=2.6.1
Requires-Dist: pymilvus>=2.5.1
Requires-Dist: python-dotenv>=1.0.0
Requires-Dist: ruff>=0.11.0
